rgblues/__init__.py
rgblues/__main__.py
rgblues/version.py
rgblues/core/__init__.py
rgblues/core/step1.py
rgblues/core/step2.py
rgblues/core/step3.py
rgblues/core/step4.py
rgblues/core/step5.py
rgblues/core/step6.py
rgblues/core/step7.py
rgblues/gui/__init__.py
rgblues/gui/step8.py
rgblues/gui/style.py
rgblues-1.4.dist-info/LICENSE
rgblues-1.4.dist-info/METADATA
rgblues-1.4.dist-info/WHEEL
rgblues-1.4.dist-info/entry_points.txt
rgblues-1.4.dist-info/top_level.txt
rgblues-1.4.dist-info/RECORD
