Metadata-Version: 2.1
Name: rgblues
Version: 1.4
Summary: RGB from Gaia EDR3
Home-page: https://github.com/guaix-ucm/rgblues
Author: Nicolás Cardiel
Author-email: cardiel@ucm.es
License: GPLv3
Classifier: Programming Language :: Python :: 3.8
Classifier: Programming Language :: Python :: 3.9
Classifier: Programming Language :: Python :: 3.10
Classifier: Programming Language :: Python :: 3.11
Classifier: Development Status :: 3 - Alpha
Classifier: Environment :: Console
Classifier: Intended Audience :: Science/Research
Classifier: License :: OSI Approved :: GNU General Public License v3 (GPLv3)
Classifier: Operating System :: OS Independent
Classifier: Topic :: Scientific/Engineering :: Astronomy
License-File: LICENSE
Requires-Dist: numpy
Requires-Dist: astropy
Requires-Dist: matplotlib
Requires-Dist: requests
Requires-Dist: astroquery
Requires-Dist: pyvo
Requires-Dist: pooch
